{"return_basis": "price", "equities": [{"series_id": "DIA", "display_name": "Dow Jones (DIA)", "price": 516.3, "ytd": 0.0743, "ret_1y": 0.2112, "asof": "2026-06-17"}, {"series_id": "EEM", "display_name": "Emerging Markets (EEM)", "price": 68.56, "ytd": 0.2532, "ret_1y": 0.4516, "asof": "2026-06-17"}, {"series_id": "EFA", "display_name": "Developed ex-US (EFA)", "price": 103.78, "ytd": 0.0807, "ret_1y": 0.1788, "asof": "2026-06-17"}, {"series_id": "EWJ", "display_name": "Japan (EWJ)", "price": 94.45, "ytd": 0.1698, "ret_1y": 0.2912, "asof": "2026-06-17"}, {"series_id": "IWM", "display_name": "Russell 2000 (IWM)", "price": 289.88, "ytd": 0.1776, "ret_1y": 0.3753, "asof": "2026-06-17"}, {"series_id": "QQQ", "display_name": "Nasdaq 100 (QQQ)", "price": 722.51, "ytd": 0.1761, "ret_1y": 0.3523, "asof": "2026-06-17"}, {"series_id": "SPY", "display_name": "S&P 500 (SPY)", "price": 740.96, "ytd": 0.0866, "ret_1y": 0.2294, "asof": "2026-06-17"}, {"series_id": "VGK", "display_name": "Europe (VGK)", "price": 89.23, "ytd": 0.0672, "ret_1y": 0.1512, "asof": "2026-06-17"}, {"series_id": "XLB", "display_name": "Materials (XLB)", "price": 52.02, "ytd": 0.1471, "ret_1y": 0.1807, "asof": "2026-06-17"}, {"series_id": "XLC", "display_name": "Communication (XLC)", "price": 109.2, "ytd": -0.0724, "ret_1y": 0.0466, "asof": "2026-06-17"}, {"series_id": "XLE", "display_name": "Energy (XLE)", "price": 54.67, "ytd": 0.2228, "ret_1y": 0.2448, "asof": "2026-06-17"}, {"series_id": "XLF", "display_name": "Financials (XLF)", "price": 54.05, "ytd": -0.0131, "ret_1y": 0.0697, "asof": "2026-06-17"}, {"series_id": "XLI", "display_name": "Industrials (XLI)", "price": 179.6, "ytd": 0.1578, "ret_1y": 0.2504, "asof": "2026-06-17"}, {"series_id": "XLK", "display_name": "Technology (XLK)", "price": 185.8, "ytd": 0.2905, "ret_1y": 0.529, "asof": "2026-06-17"}, {"series_id": "XLP", "display_name": "Consumer Staples (XLP)", "price": 83.68, "ytd": 0.0772, "ret_1y": 0.0303, "asof": "2026-06-17"}, {"series_id": "XLRE", "display_name": "Real Estate (XLRE)", "price": 43.97, "ytd": 0.0897, "ret_1y": 0.0487, "asof": "2026-06-17"}, {"series_id": "XLU", "display_name": "Utilities (XLU)", "price": 44.46, "ytd": 0.0415, "ret_1y": 0.0975, "asof": "2026-06-17"}, {"series_id": "XLV", "display_name": "Health Care (XLV)", "price": 150.71, "ytd": -0.0264, "ret_1y": 0.1105, "asof": "2026-06-17"}, {"series_id": "XLY", "display_name": "Consumer Discr. (XLY)", "price": 115.49, "ytd": -0.0328, "ret_1y": 0.0792, "asof": "2026-06-17"}], "bonds": [{"series_id": "IEF", "display_name": "7-10Y Treasuries (IEF)", "price": 94.02, "ytd": -0.0223, "ret_1y": 0.0, "asof": "2026-06-17"}, {"series_id": "SHY", "display_name": "1-3Y Treasuries (SHY)", "price": 81.88, "ytd": -0.0113, "ret_1y": -0.0063, "asof": "2026-06-17"}, {"series_id": "TLT", "display_name": "20+Y Treasuries (TLT)", "price": 86.33, "ytd": -0.0095, "ret_1y": 0.0102, "asof": "2026-06-17"}], "commodities": [{"series_id": "GLD", "display_name": "Gold (GLD)", "price": 388.6, "ytd": -0.0195, "ret_1y": 0.2464, "asof": "2026-06-17"}, {"series_id": "SLV", "display_name": "Silver (SLV)", "price": 60.61, "ytd": -0.0591, "ret_1y": 0.835, "asof": "2026-06-17"}, {"series_id": "USO", "display_name": "Crude Oil (USO)", "price": 114.23, "ytd": 0.6517, "ret_1y": 0.4535, "asof": "2026-06-17"}], "credit": [{"series_id": "HYG", "display_name": "High Yield (HYG)", "price": 79.73, "ytd": -0.0112, "ret_1y": 0.0026, "asof": "2026-06-17"}, {"series_id": "LQD", "display_name": "Inv. Grade (LQD)", "price": 108.77, "ytd": -0.0129, "ret_1y": 0.0109, "asof": "2026-06-17"}], "volatility": [{"series_id": "VIXY", "display_name": "VIX Futures (VIXY)", "price": 22.7, "ytd": -0.1147, "ret_1y": -0.5443, "asof": "2026-06-17"}], "currencies": [{"series_id": "UUP", "display_name": "US Dollar Index (UUP)", "price": 28.18, "ytd": 0.0425, "ret_1y": 0.036, "asof": "2026-06-17"}], "asof": "2026-06-17"}